signalflow/nn/__init__.py
signalflow/nn/data/__init__.py
signalflow/nn/data/signal_data_module.py
signalflow/nn/data/signal_window_dataset.py
signalflow/nn/data/ts_preprocessor.py
signalflow/nn/encoder/__init__.py
signalflow/nn/encoder/gru.py
signalflow/nn/encoder/lstm.py
signalflow/nn/head/__init__.py
signalflow/nn/head/attention_head.py
signalflow/nn/head/confidence_head.py
signalflow/nn/head/distribution_head.py
signalflow/nn/head/linear_head.py
signalflow/nn/head/mlp_head.py
signalflow/nn/head/ordinal_head.py
signalflow/nn/head/residual_head.py
signalflow/nn/layer/__init__.py
signalflow/nn/loss/__init__.py
signalflow/nn/model/__init__.py
signalflow/nn/model/temporal_classificator.py
signalflow/nn/validator/__init__.py
signalflow/nn/validator/temporal_validator.py
signalflow_nn-0.2.6.dist-info/METADATA
signalflow_nn-0.2.6.dist-info/WHEEL
signalflow_nn-0.2.6.dist-info/top_level.txt
signalflow_nn-0.2.6.dist-info/RECORD
