Metadata-Version: 2.4
Name: signalflow-nn
Version: 0.2.6
Summary: Neural network extension for signalflow (torch/lightning).
Requires-Python: >=3.12
Requires-Dist: signalflow-trading>=0.2.6
Requires-Dist: torch>=2.2
Requires-Dist: lightning>=2.5
